agentsystems_sdk/__init__.py
agentsystems_sdk/cli.py
agentsystems_sdk/config.py
agentsystems_sdk/progress_tracker.py
agentsystems_sdk/utils.py
agentsystems_sdk/commands/__init__.py
agentsystems_sdk/commands/artifacts.py
agentsystems_sdk/commands/clean.py
agentsystems_sdk/commands/down.py
agentsystems_sdk/commands/index.py
agentsystems_sdk/commands/init.py
agentsystems_sdk/commands/logs.py
agentsystems_sdk/commands/restart.py
agentsystems_sdk/commands/run.py
agentsystems_sdk/commands/status.py
agentsystems_sdk/commands/up.py
agentsystems_sdk/commands/update.py
agentsystems_sdk/commands/version.py
agentsystems_sdk/deployments_scaffold/.env.example
agentsystems_sdk/deployments_scaffold/CONTRIBUTING.md
agentsystems_sdk/deployments_scaffold/LICENSE
agentsystems_sdk/deployments_scaffold/Makefile
agentsystems_sdk/deployments_scaffold/NOTICE
agentsystems_sdk/deployments_scaffold/README.md
agentsystems_sdk/deployments_scaffold/agentsystems-config.yml
agentsystems_sdk/deployments_scaffold/requirements-dev.txt
agentsystems_sdk/deployments_scaffold/compose/langfuse/docker-compose.yml
agentsystems_sdk/deployments_scaffold/compose/local/docker-compose.yml
agentsystems_sdk/deployments_scaffold/compose/local/init-artifacts-volume.sh
agentsystems_sdk/deployments_scaffold/compose/local/db-backup/Dockerfile
agentsystems_sdk/deployments_scaffold/compose/local/db-backup/entrypoint.sh
agentsystems_sdk/deployments_scaffold/compose/local/postgres-init/audit.sql
agentsystems_sdk/deployments_scaffold/schema/agentsystems-config.schema.json
agentsystems_sdk/licenses/python/ATTRIBUTIONS.md
agentsystems_sdk/licenses/python/THIRD_PARTY_LICENSES.json
agentsystems_sdk/licenses/python/THIRD_PARTY_REQUIREMENTS.txt
agentsystems_sdk-0.5.22.dist-info/licenses/LICENSE
agentsystems_sdk-0.5.22.dist-info/licenses/NOTICE
agentsystems_sdk-0.5.22.dist-info/METADATA
agentsystems_sdk-0.5.22.dist-info/WHEEL
agentsystems_sdk-0.5.22.dist-info/entry_points.txt
agentsystems_sdk-0.5.22.dist-info/top_level.txt
agentsystems_sdk-0.5.22.dist-info/RECORD
