Metadata-Version: 2.4
Name: agentsystems-sdk
Version: 0.5.22
Summary: AgentSystems Python SDK and CLI
Author-email: AgentSystems <support@agentsystems.ai>
License-Expression: Apache-2.0
Requires-Python: >=3.11
License-File: LICENSE
License-File: NOTICE
Requires-Dist: typer[all]>=0.9
Requires-Dist: python-dotenv>=1.0
Requires-Dist: rich>=13.7
Requires-Dist: docker>=7.0
Requires-Dist: PyYAML>=6.0
Requires-Dist: requests>=2.31
Dynamic: license-file
